aql/__init__.py
aql/__version__.py
aql/column.py
aql/connector.py
aql/errors.py
aql/py.typed
aql/query.py
aql/table.py
aql/types.py
aql/engines/__init__.py
aql/engines/base.py
aql/engines/mysql.py
aql/engines/sql.py
aql/engines/sqlite.py
aql/tests/__init__.py
aql/tests/__main__.py
aql/tests/column.py
aql/tests/connector.py
aql/tests/query.py
aql/tests/table.py
aql/tests/types.py
aql/tests/engines/__init__.py
aql/tests/engines/base.py
aql/tests/engines/integration.py
aql/tests/engines/mysql.py
aql/tests/engines/sql.py
aql/tests/engines/sqlite.py
aql-0.5.0.dist-info/LICENSE
aql-0.5.0.dist-info/WHEEL
aql-0.5.0.dist-info/METADATA
aql-0.5.0.dist-info/RECORD
