Metadata-Version: 2.1
Name: aql
Version: 0.5.0
Summary: asyncio db query generator
Author-email: Amethyst Reese <amethyst@n7.gg>
Requires-Python: >=3.8
Classifier: Development Status :: 3 - Alpha
Classifier: Framework :: AsyncIO
Classifier: Intended Audience :: Developers
Classifier: License :: OSI Approved :: MIT License
Classifier: Topic :: Software Development :: Libraries
Requires-Dist: attrs >= 22
Requires-Dist: aiomysql ; extra == "all"
Requires-Dist: aiosqlite ; extra == "all"
Requires-Dist: aiomysql==0.2.0 ; extra == "dev"
Requires-Dist: aiosqlite==0.20.0 ; extra == "dev"
Requires-Dist: aiounittest==1.4.2 ; extra == "dev"
Requires-Dist: attribution==1.7.1 ; extra == "dev"
Requires-Dist: attrs==23.2.0 ; extra == "dev"
Requires-Dist: black==24.4.0 ; extra == "dev"
Requires-Dist: coverage==7.5.0 ; extra == "dev"
Requires-Dist: flake8==7 ; extra == "dev"
Requires-Dist: flake8-bugbear==24.4.21 ; extra == "dev"
Requires-Dist: flit==3.9.0 ; extra == "dev"
Requires-Dist: mypy==1.9.0 ; extra == "dev"
Requires-Dist: usort==1.0.8.post1 ; extra == "dev"
Requires-Dist: sphinx==7.3.7 ; extra == "docs"
Requires-Dist: sphinx-mdinclude==0.6.0 ; extra == "docs"
Requires-Dist: aiomysql ; extra == "mysql"
Requires-Dist: aiosqlite ; extra == "sqlite"
Project-URL: Documentation, https://aql.omnilib.dev/en/latest/
Project-URL: Github, https://github.com/omnilib/aql
Provides-Extra: all
Provides-Extra: dev
Provides-Extra: docs
Provides-Extra: mysql
Provides-Extra: sqlite
